Metadata-Version: 2.1
Name: easynewsletter
Version: 0.1.2
Summary: Newsletter module with customizable, scheduler and self-database
Home-page: https://github.com/beucismis/easynewsletter
Author: Adil Gürbüz
Author-email: beucismis@tutamail.com
License: GPL-3.0
Project-URL: Docs, https://easynewsletter.readthedocs.io
Keywords: newsletter schedule mail self-database
Platform: Linux
Platform: Windows
Platform: MacOS
Classifier: Natural Language :: English
Classifier: Intended Audience :: Developers
Classifier: Topic :: Utilities
Classifier: Topic :: Database
Classifier: Topic :: Communications :: Email
Classifier: Topic :: Software Development :: Libraries
License-File: LICENSE
